nr_events/__init__.py
nr_events/config.py
nr_events/constants.py
nr_events/ext.py
nr_events/fetchers.py
nr_events/jsonschemas/__init__.py
nr_events/jsonschemas/nr_events/__init__.py
nr_events/jsonschemas/nr_events/nr-events-v1.0.0.json
nr_events/mapping_includes/__init__.py
nr_events/mapping_includes/v7/__init__.py
nr_events/mapping_includes/v7/nr-taxonomies-nameunified-v1.0.0.json
nr_events/mappings/__init__.py
nr_events/mappings/v7/__init__.py
nr_events/mappings/v7/nr_events/nr-events-v1.0.0.json
nr_events/marshmallow/__init__.py
nr_events/marshmallow/json.py
nr_events/marshmallow/subschemas.py
nr_events/minters.py
nr_events/providers.py
nr_events/record.py
nr_events/search.py
techlib_nr_events-1.0.0a21.dist-info/entry_points.txt
techlib_nr_events-1.0.0a21.dist-info/LICENSE
techlib_nr_events-1.0.0a21.dist-info/WHEEL
techlib_nr_events-1.0.0a21.dist-info/METADATA
techlib_nr_events-1.0.0a21.dist-info/RECORD
